serverpath.py
serverpath-0.1.4.dist-info/METADATA
serverpath-0.1.4.dist-info/WHEEL
serverpath-0.1.4.dist-info/top_level.txt
serverpath-0.1.4.dist-info/RECORD
