Metadata-Version: 2.1
Name: serverpath
Version: 0.1.4
Summary: Platform-independent server-share path discovery.
Home-page: https://github.com/deluccial/serverpath.git
Author: Luke DeLuccia
Author-email: deluccial@gmail.com
License: UNKNOWN
Platform: UNKNOWN
Classifier: Programming Language :: Python :: 3.4
Classifier: Programming Language :: Python :: 3.5
Classifier: Programming Language :: Python :: 3.6
Classifier: Programming Language :: Python :: 3.7
Classifier: License :: OSI Approved :: MIT License
Classifier: Operating System :: OS Independent
